pyinsight/__init__.py
pyinsight/cleaner.py
pyinsight/dispatcher.py
pyinsight/insight.py
pyinsight/loader.py
pyinsight/merger.py
pyinsight/packager.py
pyinsight/receiver.py
pyinsight-0.3.0.dist-info/LICENSE
pyinsight-0.3.0.dist-info/METADATA
pyinsight-0.3.0.dist-info/WHEEL
pyinsight-0.3.0.dist-info/top_level.txt
pyinsight-0.3.0.dist-info/RECORD
