Metadata-Version: 2.1
Name: pyinsight
Version: 0.3.0
Summary: Insight Core Module Python Version
Home-page: https://github.com/X-I-A/pyinsight
Author: Soral
Author-email: soral@x-i-a.com
License: UNKNOWN
Platform: UNKNOWN
Classifier: Programming Language :: Python :: 3
Classifier: License :: OSI Approved :: GNU Affero General Public License v3 or later (AGPLv3+)
Classifier: Operating System :: OS Independent
Requires-Python: >=3.7
Requires-Dist: xialib
